primula/__init__.py
primula/__main__.py
primula/__version__.py
primula/_typing.py
primula/cli.py
primula/core.py
primula/exception.py
primula/lcov.py
primula/plugin.py
primula/py.typed
primula-0.6.dist-info/licenses/LICENSE.txt
primula-0.6.dist-info/METADATA
primula-0.6.dist-info/WHEEL
primula-0.6.dist-info/entry_points.txt
primula-0.6.dist-info/top_level.txt
primula-0.6.dist-info/RECORD
