Metadata-Version: 2.4
Name: primula
Version: 0.6
Summary: A code coverage tool for Vim script
Author-email: Akinori Hattori <hattya@gmail.com>
License: ALv2
Project-URL: Homepage, https://github.com/hattya/primula
Classifier: Development Status :: 3 - Alpha
Classifier: Intended Audience :: Developers
Classifier: License :: OSI Approved :: Apache Software License
Classifier: Operating System :: OS Independent
Classifier: Programming Language :: Python :: 3
Classifier: Programming Language :: Python :: 3.9
Classifier: Programming Language :: Python :: 3.10
Classifier: Programming Language :: Python :: 3.11
Classifier: Programming Language :: Python :: 3.12
Classifier: Programming Language :: Python :: 3.13
Classifier: Topic :: Software Development :: Quality Assurance
Classifier: Topic :: Software Development :: Testing
Requires-Python: >=3.9
License-File: LICENSE.txt
Requires-Dist: coverage>=5.0
Dynamic: license-file
